{
  "Routes": [
    {
      "DownstreamPathTemplate": "/api/user/{everything}",
      "DownstreamScheme": "https",
      "DownstreamHostAndPorts": [
        { "Host": "localhost", "Port": 7024 }
      ],
      "UpstreamPathTemplate": "/users/{everything}",
      "UpstreamHttpMethod": [ "GET", "POST", "PUT", "DELETE" ]
    },
    {
      "DownstreamPathTemplate": "/api/space/{everything}",
      "DownstreamScheme": "https",
      "DownstreamHostAndPorts": [
        { "Host": "localhost", "Port": 7024 }
      ],
      "UpstreamPathTemplate": "/spaces/{everything}",
      "UpstreamHttpMethod": [ "GET", "POST", "PUT", "DELETE" ]
    },
    {
      "DownstreamPathTemplate": "/api/space/{spaceId}/chat/{everything}",
      "DownstreamScheme": "https",
      "DownstreamHostAndPorts": [
        { "Host": "localhost", "Port": 7027 }
      ],
      "UpstreamPathTemplate": "/space/{spaceId}/chats/{everything}",
      "UpstreamHttpMethod": [ "GET", "POST", "PUT", "DELETE" ]
    },
    {
      "DownstreamPathTemplate": "/api/space/{spaceId}/chat/{chatId}/messages",
      "DownstreamScheme": "https",
      "DownstreamHostAndPorts": [
        { "Host": "localhost", "Port": 7027 }
      ],
      "UpstreamPathTemplate": "/space/{spaceId}/chat/{chatId}/messages",
      "UpstreamHttpMethod": [ "GET", "POST", "PUT", "DELETE" ]
    }
  ],
  "GlobalConfiguration": {
    "BaseUrl": "http://localhost:5010"
  }
}